django_celery_async_view/__init__.py
django_celery_async_view/dev_settings.py
django_celery_async_view/models.py
django_celery_async_view/storage.py
django_celery_async_view/task_helpers.py
django_celery_async_view/views.py
django_celery_async_view/migrations/0001_initial.py
django_celery_async_view/migrations/__init__.py
django_celery_async_view/static/django_celery_async_view/django_celery_async_view.js
django_celery_async_view-0.1.0.dist-info/DESCRIPTION.rst
django_celery_async_view-0.1.0.dist-info/METADATA
django_celery_async_view-0.1.0.dist-info/RECORD
django_celery_async_view-0.1.0.dist-info/WHEEL
django_celery_async_view-0.1.0.dist-info/metadata.json
django_celery_async_view-0.1.0.dist-info/top_level.txt
