Metadata-Version: 2.0
Name: django-celery-async-view
Version: 0.1.0
Summary: Asynchronously load view or download file in django.
Home-page: https://github.com/EeroPaukkonen/django_celery_async_view
Author: Eero Paukkonen
Author-email: eero.paukkonen@gmail.com
License: MIT
Keywords: django_celery_async_view,django,celery
Platform: UNKNOWN
Classifier: Development Status :: 3 - Alpha
Classifier: Framework :: Django
Classifier: Framework :: Django :: 1.8
Classifier: Framework :: Django :: 1.9
Classifier: Framework :: Django :: 1.10
Classifier: Intended Audience :: Developers
Classifier: License :: OSI Approved :: MIT License
Classifier: Natural Language :: English
Classifier: Programming Language :: Python :: 2
Classifier: Programming Language :: Python :: 2.7
Requires-Dist: django-db-file-storage (==0.4.3)
